<?xml version="1.0"?>
<root>
   <mesh repertoire="/utmp/muscadet/damage/PROJET1.files/PR4/" nom_qualif="S_PR4_2d.qualif" nom_maillage="S_PR4_2d.mail" nb_maillage="385" echelle="0.0001" unit="mm/pix"/>
   <formulation type="isotrope" resolution="contrainte_plane" />
   <materials>
         <coefficients type="isotrope" resolution="contrainte_plane" id="0" name="matrice"  young_modulus="20e3" poisson_ratio="0.3" unit="MPa" thickness="1"
         alpha="30e-6" deltaT = "150"/>
         <coefficients type="isotrope" resolution="contrainte_plane" id="1" name="fibre"  young_modulus="20e3" poisson_ratio="0.3" unit="MPa" thickness="1" alpha="30e-6" deltaT = "150"/>
   </materials>
    <proprietes_interfaces>
         <coefficients Gcrit="0.005" unitG="N/mm"  coeffrottement="0.3" box="0 0 0 0" name="fibre-matrice"/>
         <coefficients Gcrit="0.002" unitG="N/mm" coeffrottement="0.3"  box="0 0 0 0" name="matrice-matrice"/>
   </proprietes_interfaces>
   
   <parametres sous_integration="non" nbmacro="4" multi="4" rbm="0" nbiter="200" facteur_relaxation="0.8" errorcrit="1e-4" nb_threads="1"/>
   <parametres_temporels nbpastemps="20" pasdetemps="1" />
   <parametres_affichage affichmesh="0" affichres="0" typeaffich="Sinterieur" save_affichage="save" afficherror="0" repertoiresauv="./tmp/"/>
   <direction_recherche ktype="3" kfact="2e6" formule="E/L" copydirection="1" />
   
   <CL box="0 0 0 1500" unit="pixel" comp="Eff" val_spatiale="-80 0"  val_temporelle_ini_coefdir="1 0.05"/>
   <CL box="1500 0 1500 1500" unit="pixel"  comp="Eff" val_spatiale="80 0" val_temporelle_ini_coefdir="1 0.05"/>
   
   <parametres_micro nbinterdeg="6" boxdegrad="200 200 1300 1300" unit="pixel" />
   
</root>
